Metadata-Version: 2.1
Name: filecrypter
Version: 3.11
Summary: Script to Help Encrypt and Decrypt File Using RSA Key.
Home-page: https://github.com/fuadkhan713/filecrypter
Author: Fuad Khan
Author-email: fuad.khan713@gmail.com
License: UNKNOWN
Project-URL: Documentation, https://packaging.python.org/tutorials/distributing-packages/
Project-URL: Funding, https://donate.pypi.org
Project-URL: Source, https://github.com/fuadkhan713/filecrypter
Project-URL: Tracker, https://github.com/fuadkhan713/filecrypter/issues
Platform: UNKNOWN
Classifier: Development Status :: 4 - Beta
Classifier: Intended Audience :: Education
Classifier: Programming Language :: Python :: 3.7
Classifier: Programming Language :: Python :: 3.8
Classifier: Programming Language :: Python :: 3.9
Classifier: Topic :: Security :: Cryptography 
Classifier: Topic :: System :: Networking
Requires-Python: >=3.7
